cloud_components/application/errors/invalid_resource.py
cloud_components/application/interface/infra/builder.py
cloud_components/application/interface/infra/event.py
cloud_components/application/interface/infra/function.py
cloud_components/application/interface/infra/queue.py
cloud_components/application/interface/infra/storage.py
cloud_components/application/interface/services/env/enviroment.py
cloud_components/application/interface/services/enviroment/enviroment.py
cloud_components/application/interface/services/log/builder.py
cloud_components/application/interface/services/log/logger.py
cloud_components/application/types/aws.py
cloud_components/application/types/gcp.py
cloud_components/infra/aws/builder.py
cloud_components/infra/aws/connection/connector_factory.py
cloud_components/infra/aws/connection/resource_connector.py
cloud_components/infra/aws/resources/lambda_function.py
cloud_components/infra/aws/resources/s3.py
cloud_components/infra/aws/resources/sns.py
cloud_components/infra/aws/resources/sqs.py
cloud_components/infra/factory.py
cloud_components/infra/gcp/builder.py
cloud_components/infra/gcp/connection/connector_factory.py
cloud_components/infra/gcp/connection/resource_connector.py
cloud_components/infra/gcp/resources/storage.py
cloud_components/services/env/dotenv.py
cloud_components/services/env/factory.py
cloud_components/services/log/builder.py
cloud_components-3.1.0.dist-info/LICENSE
cloud_components-3.1.0.dist-info/METADATA
cloud_components-3.1.0.dist-info/WHEEL
cloud_components-3.1.0.dist-info/RECORD
