Metadata-Version: 2.1
Name: cloud-components
Version: 3.1.0
Summary: 
License: MIT
Author: Giovani Liskoski Zanini
Author-email: giovanilzanini@hotmail.com
Requires-Python: >=3.9
Classifier: License :: OSI Approved :: MIT License
Classifier: Programming Language :: Python :: 3
Classifier: Programming Language :: Python :: 3.9
Classifier: Programming Language :: Python :: 3.10
Classifier: Programming Language :: Python :: 3.11
Classifier: Programming Language :: Python :: 3.12
